LICENSE
dlna_cast/__init__.py
dlna_cast/main.py
dlna_cast/ssdp.py
dlna_cast-0.1.8.dist-info/LICENSE
dlna_cast-0.1.8.dist-info/METADATA
dlna_cast-0.1.8.dist-info/WHEEL
dlna_cast-0.1.8.dist-info/entry_points.txt
dlna_cast-0.1.8.dist-info/RECORD
