Metadata-Version: 2.1
Name: dlna-cast
Version: 0.1.8
Summary: A cross-platform command-line tool that casts screen and media file to remote DLNA device.
License: GPL-3.0-or-later
Keywords: DLNA,ffmpeg,media,smart-tv,screen-cast,uPnP
Author: weihong.xu
Author-email: xuweihong.cn@gmail.com
Requires-Python: >=3.7,<4.0
Classifier: Environment :: Console
Classifier: License :: OSI Approved :: GNU General Public License v3 or later (GPLv3+)
Classifier: Operating System :: OS Independent
Classifier: Programming Language :: Python :: 3
Classifier: Programming Language :: Python :: 3.7
Classifier: Programming Language :: Python :: 3.8
Classifier: Programming Language :: Python :: 3.9
Classifier: Programming Language :: Python :: 3.10
Classifier: Programming Language :: Python :: 3.11
Classifier: Programming Language :: Python :: 3.12
Requires-Dist: fire (>=0.4.0,<0.5.0)
Requires-Dist: python-dotenv[cli] (>=0.21.0,<0.22.0)
Requires-Dist: upnpclient (>=1.0.3,<2.0.0)
